coiled_runtime/__init__.py
coiled_runtime-0.2.1.dist-info/LICENSE
coiled_runtime-0.2.1.dist-info/METADATA
coiled_runtime-0.2.1.dist-info/WHEEL
coiled_runtime-0.2.1.dist-info/top_level.txt
coiled_runtime-0.2.1.dist-info/RECORD
