Metadata-Version: 2.1
Name: coiled-runtime
Version: 0.2.1
Summary: Simple and fast way to get started with Dask
Home-page: https://github.com/coiled/coiled-runtime
License: BSD
Classifier: Programming Language :: Python :: 3
Classifier: Programming Language :: Python :: 3.8
Classifier: Programming Language :: Python :: 3.9
Classifier: Programming Language :: Python :: 3.10
Classifier: License :: OSI Approved :: BSD License
Requires-Python: <3.11,>=3.8
License-File: LICENSE
Requires-Dist: pip
Requires-Dist: coiled (>=0.2.41)
Requires-Dist: numpy (==1.23.5)
Requires-Dist: pandas (==1.5.2)
Requires-Dist: dask (==2022.11.1)
Requires-Dist: distributed (==2022.11.1)
Requires-Dist: fsspec (==2022.11.0)
Requires-Dist: s3fs (==2022.11.0)
Requires-Dist: gcsfs (==2022.11.0)
Requires-Dist: pyarrow (==10.0.1)
Requires-Dist: jupyterlab (==3.5.0)
Requires-Dist: dask-labextension (==6.0.0)
Requires-Dist: lz4 (==4.0.2)
Requires-Dist: ipywidgets (==7.7.2)
Requires-Dist: numba (==0.56.3)
Requires-Dist: scikit-learn (==1.1.3)
Requires-Dist: ipycytoscape (==1.3.3)
Requires-Dist: click (==8.1.3)
Requires-Dist: xarray (==2022.11.0)
Requires-Dist: zarr (==2.13.3)
Requires-Dist: cloudpickle (==2.2.0)
Requires-Dist: tornado (==6.1)
Requires-Dist: toolz (==0.12.0)
Requires-Dist: zict (==2.2.0)
Requires-Dist: xgboost (==1.7.1)
Requires-Dist: dask-ml (==2022.5.27)
Requires-Dist: pynvml (==11.4.1)
Requires-Dist: bokeh (==2.4.3)
Requires-Dist: msgpack (==1.0.4)
